{
  "project_info": {
    "project_number": "513457495739",
    "firebase_url": "https://spikeboost-bbdc8.firebaseio.com",
    "project_id": "spikeboost-bbdc8",
    "storage_bucket": "spikeboost-bbdc8.appspot.com"
  },
  "client": [
    {
      "client_info": {
        "mobilesdk_app_id": "1:513457495739:android:78a9aaa54c611d42",
        "android_client_info": {
          "package_name": "com.spayker.spikeboost"
        }
      },
      "oauth_client": [
        {
          "client_id": "513457495739-v2i1b90dhk3df9l09rqjjcpf53gk69lg.apps.googleusercontent.com",
          "client_type": 3
        }
      ],
      "api_key": [
        {
          "current_key": "AIzaSyAIA7vNTPKECj7PBWpOJHtV2m6C_4IkgBQ"
        }
      ],
      "services": {
        "analytics_service": {
          "status": 1
        },
        "appinvite_service": {
          "status": 1,
          "other_platform_oauth_client": []
        },
        "ads_service": {
          "status": 2
        }
      }
    }
  ],
  "configuration_version": "1"
}